setup.py
rubik_box/__init__.py
rubik_box/rubik_box.py
rubik_box.egg-info/PKG-INFO
rubik_box.egg-info/SOURCES.txt
rubik_box.egg-info/dependency_links.txt
rubik_box.egg-info/requires.txt
rubik_box.egg-info/top_level.txt
rubik_box.egg-info/zip-safe