Metadata-Version: 1.1
Name: rubik-box
Version: 0.0.2
Summary: Rubik's cube solver
Home-page: https://github.com/colonelmo/rubik-box
Author: Mohammad Nasirifar
Author-email: far.nasiri.m@gmail.com
License: Beerware
Keywords: rubik rubik's cube solver
Platform: UNKNOWN
Classifier: Development Status :: 3 - Alpha
Classifier: Environment :: Console
Classifier: Intended Audience :: End Users/Desktop
Classifier: License :: Other/Proprietary License
Classifier: Operating System :: POSIX :: Linux
Classifier: Programming Language :: Python
Classifier: Topic :: Games/Entertainment :: Puzzle Games
